pyhman/__init__.py
pyhman/hman.py
pyhman/hmanserver.py
pyhman-1.0.3.dist-info/LICENSE
pyhman-1.0.3.dist-info/METADATA
pyhman-1.0.3.dist-info/WHEEL
pyhman-1.0.3.dist-info/top_level.txt
pyhman-1.0.3.dist-info/RECORD
