Metadata-Version: 2.1
Name: pyhman
Version: 1.0.3
Summary: Python library to control the HMan robot
Home-page: UNKNOWN
Author: Alexis Devillard
License: MIT
Platform: UNKNOWN
License-File: LICENSE
